odoo/addons/ssi_work_log_mixin/README.rst
odoo/addons/ssi_work_log_mixin/__init__.py
odoo/addons/ssi_work_log_mixin/__manifest__.py
odoo/addons/ssi_work_log_mixin/menu.xml
odoo/addons/ssi_work_log_mixin/data/approval_template_data.xml
odoo/addons/ssi_work_log_mixin/data/ir_sequence_data.xml
odoo/addons/ssi_work_log_mixin/data/policy_template_data.xml
odoo/addons/ssi_work_log_mixin/data/sequence_template_data.xml
odoo/addons/ssi_work_log_mixin/models/__init__.py
odoo/addons/ssi_work_log_mixin/models/account_analytic_account.py
odoo/addons/ssi_work_log_mixin/models/hr_timesheet.py
odoo/addons/ssi_work_log_mixin/models/hr_work_log.py
odoo/addons/ssi_work_log_mixin/models/hr_work_log_tag.py
odoo/addons/ssi_work_log_mixin/models/ir_model.py
odoo/addons/ssi_work_log_mixin/models/mixin_work_object.py
odoo/addons/ssi_work_log_mixin/report/__init__.py
odoo/addons/ssi_work_log_mixin/report/hr_project_work_log_analysis.py
odoo/addons/ssi_work_log_mixin/report/hr_project_work_log_analysis.xml
odoo/addons/ssi_work_log_mixin/report/hr_work_log_analysis.py
odoo/addons/ssi_work_log_mixin/report/hr_work_log_analysis.xml
odoo/addons/ssi_work_log_mixin/security/ir.model.access.csv
odoo/addons/ssi_work_log_mixin/security/ir_module_category_data.xml
odoo/addons/ssi_work_log_mixin/security/ir_rule_data.xml
odoo/addons/ssi_work_log_mixin/security/res_group_data.xml
odoo/addons/ssi_work_log_mixin/static/description/icon.png
odoo/addons/ssi_work_log_mixin/templates/work_log_mixin_templates.xml
odoo/addons/ssi_work_log_mixin/views/account_analytic_account_views.xml
odoo/addons/ssi_work_log_mixin/views/hr_timesheet_views.xml
odoo/addons/ssi_work_log_mixin/views/hr_work_log_tag_views.xml
odoo/addons/ssi_work_log_mixin/views/hr_work_log_views.xml
odoo/addons/ssi_work_log_mixin/views/ir_model_views.xml
odoo14_addon_ssi_work_log_mixin-14.0.1.19.0.dist-info/METADATA
odoo14_addon_ssi_work_log_mixin-14.0.1.19.0.dist-info/WHEEL
odoo14_addon_ssi_work_log_mixin-14.0.1.19.0.dist-info/top_level.txt
odoo14_addon_ssi_work_log_mixin-14.0.1.19.0.dist-info/RECORD
